txdbus/__init__.py
txdbus/authentication.py
txdbus/bus.py
txdbus/client.py
txdbus/endpoints.py
txdbus/error.py
txdbus/interface.py
txdbus/introspection.py
txdbus/marshal.py
txdbus/message.py
txdbus/objects.py
txdbus/protocol.py
txdbus/router.py
txdbus-1.1.0.dist-info/DESCRIPTION.rst
txdbus-1.1.0.dist-info/METADATA
txdbus-1.1.0.dist-info/RECORD
txdbus-1.1.0.dist-info/WHEEL
txdbus-1.1.0.dist-info/metadata.json
txdbus-1.1.0.dist-info/top_level.txt
