Metadata-Version: 2.0
Name: txdbus
Version: 1.1.0
Summary: A native Python implementation of the DBus protocol for Twisted applications.
Home-page: https://github.com/cocagne/txdbus
Author: Tom Cocagne
Author-email: tom.cocagne@gmail.com
License: MIT
Keywords: dbus,twisted
Platform: UNKNOWN
Classifier: Development Status :: 4 - Beta
Classifier: Framework :: Twisted
Classifier: Intended Audience :: Developers
Classifier: License :: OSI Approved :: MIT License
Classifier: Operating System :: POSIX
Classifier: Programming Language :: Python :: 2.7
Classifier: Programming Language :: Python :: 3.3
Classifier: Programming Language :: Python :: 3.4
Classifier: Programming Language :: Python :: 3.5
Classifier: Programming Language :: Python :: 3.6
Classifier: Topic :: Software Development :: Libraries
Classifier: Topic :: System :: Networking
Provides: txdbus
Requires-Dist: six
Requires-Dist: twisted (>=10.1)
